[
  {
    "analysisId": 1,
    "description": "Matching plus simple outcome model",
    "getDbCohortMethodDataArgs": {
      "studyStartDate": "",
      "studyEndDate": "",
      "excludeDrugsFromCovariates": true,
      "firstExposureOnly": true,
      "removeDuplicateSubjects": true,
      "restrictToCommonPeriod": false,
      "washoutPeriod": 365,
      "covariateSettings": {
        "useCovariateDemographics": true,
        "useCovariateDemographicsGender": false,
        "useCovariateDemographicsRace": false,
        "useCovariateDemographicsEthnicity": false,
        "useCovariateDemographicsAge": false,
        "useCovariateDemographicsYear": false,
        "useCovariateDemographicsMonth": false,
        "useCovariateConditionOccurrence": true,
        "useCovariateConditionOccurrenceLongTerm": true,
        "useCovariateConditionOccurrenceShortTerm": true,
        "useCovariateConditionOccurrenceInptMediumTerm": true,
        "useCovariateConditionEra": true,
        "useCovariateConditionEraEver": true,
        "useCovariateConditionEraOverlap": true,
        "useCovariateConditionGroup": true,
        "useCovariateConditionGroupMeddra": false,
        "useCovariateConditionGroupSnomed": false,
        "useCovariateDrugExposure": true,
        "useCovariateDrugExposureLongTerm": true,
        "useCovariateDrugExposureShortTerm": true,
        "useCovariateDrugEra": true,
        "useCovariateDrugEraLongTerm": true,
        "useCovariateDrugEraShortTerm": true,
        "useCovariateDrugEraOverlap": true,
        "useCovariateDrugEraEver": true,
        "useCovariateDrugGroup": true,
        "useCovariateProcedureOccurrence": true,
        "useCovariateProcedureOccurrenceLongTerm": true,
        "useCovariateProcedureOccurrenceShortTerm": true,
        "useCovariateProcedureGroup": true,
        "useCovariateObservation": true,
        "useCovariateObservationLongTerm": true,
        "useCovariateObservationShortTerm": true,
        "useCovariateObservationCountLongTerm": true,
        "useCovariateMeasurement": false,
        "useCovariateMeasurementLongTerm": true,
        "useCovariateMeasurementShortTerm": true,
        "useCovariateMeasurementCountLongTerm": true,
        "useCovariateMeasurementBelow": true,
        "useCovariateMeasurementAbove": true,
        "useCovariateConceptCounts": true,
        "useCovariateRiskScores": true,
        "useCovariateRiskScoresCharlson": true,
        "useCovariateRiskScoresDCSI": true,
        "useCovariateRiskScoresCHADS2": true,
        "useCovariateRiskScoresCHADS2VASc": false,
        "useCovariateInteractionYear": false,
        "useCovariateInteractionMonth": false,
        "addDescendantsToExclude": true,
        "addDescendantsToInclude": true,
        "deleteCovariatesSmallCount": 100,
        "longTermDays": 365,
        "mediumTermDays": 180,
        "shortTermDays": 30,
        "windowEndDays": 0,
        "attr_fun": "getDbDefaultCovariateData",
        "attr_class": "covariateSettings"
      },
      "attr_class": "args"
    },
    "createStudyPopArgs": {
      "firstExposureOnly": false,
      "restrictToCommonPeriod": false,
      "washoutPeriod": 0,
      "removeDuplicateSubjects": false,
      "removeSubjectsWithPriorOutcome": true,
      "priorOutcomeLookback": 99999,
      "minDaysAtRisk": 1,
      "riskWindowStart": 0,
      "addExposureDaysToStart": false,
      "riskWindowEnd": 0,
      "addExposureDaysToEnd": true,
      "attr_class": "args"
    },
    "createPs": true,
    "createPsArgs": {
      "errorOnHighCorrelation": true,
      "stopOnError": true,
      "prior": {
        "priorType": "laplace",
        "variance": 1,
        "exclude": 0,
        "graph": null,
        "neighborhood": null,
        "useCrossValidation": true,
        "forceIntercept": false,
        "attr_class": "cyclopsPrior"
      },
      "control": {
        "maxIterations": 1000,
        "tolerance": 2e-007,
        "convergenceType": "gradient",
        "autoSearch": true,
        "fold": 10,
        "lowerLimit": 0.01,
        "upperLimit": 20,
        "gridSteps": 10,
        "minCVData": 100,
        "cvRepetitions": 1,
        "noiseLevel": "quiet",
        "threads": 1,
        "seed": null,
        "resetCoefficients": false,
        "startingVariance": 0.01,
        "useKKTSwindle": false,
        "tuneSwindle": 10,
        "selectorType": "auto",
        "initialBound": 2,
        "maxBoundCount": 5,
        "attr_class": "cyclopsControl"
      },
      "attr_class": "args"
    },
    "trimByPs": false,
    "trimByPsToEquipoise": false,
    "matchOnPs": true,
    "matchOnPsArgs": {
      "caliper": 0.2,
      "caliperScale": "standardized logit",
      "maxRatio": 100,
      "attr_class": "args"
    },
    "matchOnPsAndCovariates": false,
    "stratifyByPs": false,
    "stratifyByPsAndCovariates": false,
    "computeCovariateBalance": false,
    "fitOutcomeModel": true,
    "fitOutcomeModelArgs": {
      "modelType": "cox",
      "stratified": true,
      "useCovariates": false,
      "prior": {
        "priorType": "laplace",
        "variance": 1,
        "exclude": null,
        "graph": null,
        "neighborhood": null,
        "useCrossValidation": true,
        "forceIntercept": false,
        "attr_class": "cyclopsPrior"
      },
      "control": {
        "maxIterations": 1000,
        "tolerance": 2e-007,
        "convergenceType": "gradient",
        "autoSearch": true,
        "fold": 10,
        "lowerLimit": 0.01,
        "upperLimit": 20,
        "gridSteps": 10,
        "minCVData": 100,
        "cvRepetitions": 10,
        "noiseLevel": "quiet",
        "threads": 1,
        "seed": null,
        "resetCoefficients": false,
        "startingVariance": 0.01,
        "useKKTSwindle": false,
        "tuneSwindle": 10,
        "selectorType": "auto",
        "initialBound": 2,
        "maxBoundCount": 5,
        "attr_class": "cyclopsControl"
      },
      "attr_class": "args"
    },
    "attr_class": "cmAnalysis"
  }
]
